{
    "1":{
        "name": "Vydaj PnR na rok 2025",
        "type": "text",
        "text": "Výdaj povolení na rybolov (PnR) pre rok 2025 bude v dňoch 09. 01. 2025, 06. 02. 2025, 27. 03. 2025, 10. 04. 2025, 15. 05. 2025, 05. 06. 2025, v čase od 16:30 do 18:00 hod v rybárskom dome na ul. Májovej v Medzilaborciach. Výdaj PnR bude aj pred konaním výročnej členskej schôdze (VČS) a to hodinu pred jej zčatím (dátum, miesto a čas konania VČS bude v predstihu upresnený).Platbu za PnR je potrebné posielať na číslo účtu:SK42 0200 0000 0047 0429 0059 účet je vedený vo WUB banke. Do poznámky/správy pri úhrade je potrené uviesť za koho je úhrada vykonaná a za aký druh povolenia. Ak v texte nebude uvedené za koho a za aký druh PnR je úhrada vykonaná, bude úhrada spätne vrátená odosielateľovi!!! Ak niekto nemá prístup k internetbankingu bude mu vydaný poštový poukaz."
    },
    "2":{
        "name": "Ceny PnR na rok 2025",
        "type": "table",

        "text": {
                "1": ["Členské známky"],
                "3": ["DETI ( do dovŕšenia 6 roku )", "3 €"],
                "4": ["DETI (6 – 14 rokov)", "3 €"],
                "5": ["MLÁDEŽ (15 – 17 rokov)", "20€"],
                "6": ["DOSPELÍ", "35€"],
        
                "10": ["Zápisné"],
                "11": ["DETI ( do dovŕšenia 6 roku )", "0 €"],
                "12": ["DETI (6 – 14 rokov)", "3 €"],
                "13": ["MLÁDEŽ (15 – 17 rokov)", "5 €"],
                "14": ["DOSPELÍ", "50€"],
        
                "20": ["Povolenia na rybolov"],
                "21": ["Mieste pstruhové (PnR) - DETI (6 – 14 rokov)", "15 €"],
                "22": ["Mieste kaprové (PnR) - DETI (6 – 14 rokov)", "10 €"],
                "23": ["Zväzové kaprové (PnR) - DETI (6 – 14 rokov)", "15 €"],
                "24": ["Mieste pstruhové (PnR) - MLÁDEŽ (15 – 17 rokov)", "27 €"],
                "25": ["Mieste kaprové (PnR) - MLÁDEŽ (15 – 17 rokov)", "40 €"],
                "26": ["Zväzové kaprové (PnR) - MLÁDEŽ (15 – 17 rokov)", "75 €"],
                "27": ["Mieste pstruhové (PnR) - DOSPELÍ", "27 €"],
                "28": ["Mieste kaprové (PnR) - DOSPELÍ", "40 €"],
                "29": ["Zväzové kaprové (PnR) - DOSPELÍ", "75 €"],
        
                "30": ["Tlačivá"],
                "31": ["Tlačivá", "1 €"],
                "32": ["Tlačivá pre nových členov", "3 €"],
        
                "40": ["Sumárne poplatky pre členov"],
                "41": ["Deti miestne kaprové (PnR) (6 – 14 rokov)", "14 €"],
                "42": ["Deti miestne pstruhové (PnR) (6 – 14 rokov)", "15 €"],
                "43": ["Mládež miestne kaprové (PnR) (15 – 17 rokov)", "61 €"],
                "44": ["Mládež miestne pstruhové (PnR) (15 – 17 rokov)", "27 €"],
                "45": ["Dospelí miestne kaprové (PnR)", "76 €"],
                "46": ["Dospelí miestne pstruhové (PnR)", "27 €"],
                "47": ["Deti zväzové (PnR) (6 – 14 rokov)", "29 €"],
                "48": ["Mládež zväzové (PnR) (15 – 17 rokov)", "136 €"],
                "49": ["Dospelí zväzové (PnR)", "151 €"],
        
                "50": ["Sumárne poplatky pre nových členov"],
                "51": ["Deti (PnR) - (6 – 14 rokov)", "31 €"],
                "52": ["Deti miestne pstruhové (PnR) (6 – 14 rokov)", "15 €"],
                "53": ["Mládež (PnR) - (15 – 17 rokov)", "143 €"],
                "54": ["Mládež miestne pstruhové (PnR) (15 – 17 rokov)", "27 €"],
                "55": ["Dospelí (PnR)", "203 €"],
                "56": ["Dospelí miestne pstruhové (PnR)", "27 €"],
        
                "60": ["Iné poplatky"],
                "61": ["Odovzdaný záznam o úlovkoch, ale nevyplnený za rok 2024", "20 €"],
                "62": ["Neodpracovanie brigády za rok 2024", "30 €"]
            }
        
    },
    "3":{
        "name": "Rybarský listok",
        "type": "text",
        "text": "Oddnes je možnosť zakúpiť si priamo v domčeku MO SRZ Medzilaborce RYBARSKY LÍSTOK (týždenný 1.50.- , mesačný 3.- , ročný 7.- , trojročný 17.-).Osoby oslobodené od poplatku sú - žiaci a študenti stredných a vysokých škôl študijných odborov s výučbou rybárstva, zamestnanci štátnej správy s ústredným riadením rybárstva, ktorí majú v pracovnej zmluve aktívne vykonávanie rybárstva, odborní zamestnanci na úseku rybárstva, ak majú vykonávanie rybárstva vo svojej pracovnej zmluve, zamestnanci Slovenského rybárskeho zväzu, rybárski hospodári a ich zástupcovia a osoby ustanovené ako rybárska stráž po predložení potvrdenia o výkone pracovnej náplne alebo povolania, cudzinci, ktorí prídu do Slovenskej republiky na pozvanie alebo so súhlasom prezidenta Slovenskej republiky, Národnej rady Slovenskej republiky a vlády Slovenskej republiky, osoby do 15 rokov."
    },
    "4":{
        "name": "Platba",
        "type": "text",
        "text": "Platbu za PnR je potrebné posielať LEN na číslo účtu: SK42 0200 0000 0047 0429 0059 účet je vedený vo VUB banke. Kde je potrebné do poznámky/správy uviesť za koho je úhrada robená a za aký druh povolenia je úhrada!!! Pokiaľ nemá niekto prístup k internetbankingu bude mu vydaný poštový poukaz."
    }
}